cqrs/__init__.py
cqrs/mediator.py
cqrs/producer.py
cqrs/response.py
cqrs/types.py
cqrs/adapters/__init__.py
cqrs/adapters/amqp.py
cqrs/adapters/circuit_breaker.py
cqrs/adapters/kafka.py
cqrs/adapters/protocol.py
cqrs/compressors/__init__.py
cqrs/compressors/protocol.py
cqrs/compressors/zlib.py
cqrs/container/__init__.py
cqrs/container/dependency_injector.py
cqrs/container/di.py
cqrs/container/protocol.py
cqrs/deserializers/__init__.py
cqrs/deserializers/exceptions.py
cqrs/deserializers/json.py
cqrs/dispatcher/__init__.py
cqrs/dispatcher/event.py
cqrs/dispatcher/exceptions.py
cqrs/dispatcher/models.py
cqrs/dispatcher/request.py
cqrs/dispatcher/saga.py
cqrs/dispatcher/streaming.py
cqrs/events/__init__.py
cqrs/events/bootstrap.py
cqrs/events/event.py
cqrs/events/event_emitter.py
cqrs/events/event_handler.py
cqrs/events/event_processor.py
cqrs/events/map.py
cqrs/message_brokers/__init__.py
cqrs/message_brokers/amqp.py
cqrs/message_brokers/devnull.py
cqrs/message_brokers/kafka.py
cqrs/message_brokers/protocol.py
cqrs/middlewares/__init__.py
cqrs/middlewares/base.py
cqrs/middlewares/logging.py
cqrs/outbox/__init__.py
cqrs/outbox/map.py
cqrs/outbox/mock.py
cqrs/outbox/repository.py
cqrs/outbox/sqlalchemy.py
cqrs/requests/__init__.py
cqrs/requests/bootstrap.py
cqrs/requests/cor_request_handler.py
cqrs/requests/map.py
cqrs/requests/mermaid.py
cqrs/requests/request.py
cqrs/requests/request_handler.py
cqrs/saga/__init__.py
cqrs/saga/bootstrap.py
cqrs/saga/circuit_breaker.py
cqrs/saga/compensation.py
cqrs/saga/execution.py
cqrs/saga/fallback.py
cqrs/saga/mermaid.py
cqrs/saga/models.py
cqrs/saga/recovery.py
cqrs/saga/saga.py
cqrs/saga/step.py
cqrs/saga/validation.py
cqrs/saga/storage/__init__.py
cqrs/saga/storage/enums.py
cqrs/saga/storage/memory.py
cqrs/saga/storage/models.py
cqrs/saga/storage/protocol.py
cqrs/saga/storage/sqlalchemy.py
cqrs/serializers/__init__.py
cqrs/serializers/default.py
python_cqrs-4.7.3.dist-info/licenses/LICENSE
python_cqrs-4.7.3.dist-info/METADATA
python_cqrs-4.7.3.dist-info/WHEEL
python_cqrs-4.7.3.dist-info/top_level.txt
python_cqrs-4.7.3.dist-info/RECORD
