Metadata-Version: 2.4
Name: python-cqrs
Version: 4.7.3
Summary: Python CQRS pattern implementation
Author-email: Vadim Kozyrevskiy <vadikko2@mail.ru>, Dmitry Kutlubaev <kutlubaev00@mail.ru>
Maintainer-email: Vadim Kozyrevskiy <vadikko2@mail.ru>
Project-URL: Documentation, https://mkdocs.python-cqrs.dev/
Project-URL: Issues, https://github.com/vadikko2/python-cqrs/issues
Project-URL: Repository, https://github.com/vadikko2/python-cqrs
Classifier: Development Status :: 4 - Beta
Classifier: License :: OSI Approved :: MIT License
Classifier: Operating System :: OS Independent
Classifier: Programming Language :: Python :: 3.10
Classifier: Programming Language :: Python :: 3.11
Classifier: Programming Language :: Python :: 3.12
Requires-Python: >=3.10
License-File: LICENSE
Requires-Dist: dataclass-wizard==0.*
Requires-Dist: di[anyio]==0.79.2
Requires-Dist: dependency-injector>=4.48.2
Requires-Dist: orjson==3.*
Requires-Dist: pydantic==2.*
Requires-Dist: python-dotenv==1.0.1
Requires-Dist: retry-async==0.1.4
Requires-Dist: sqlalchemy[asyncio]==2.0.*
Requires-Dist: typing-extensions>=4.0.0
Provides-Extra: aiobreaker
Requires-Dist: aiobreaker>=0.3.0; extra == "aiobreaker"
Provides-Extra: dev
Requires-Dist: pycln==2.5.0; extra == "dev"
Requires-Dist: pre-commit==3.8.0; extra == "dev"
Requires-Dist: pyright==1.1.408; extra == "dev"
Requires-Dist: ruff==0.6.2; extra == "dev"
Requires-Dist: vermin>=1.6.0; extra == "dev"
Requires-Dist: pytest-cov>=4.0.0; extra == "dev"
Requires-Dist: pytest-codspeed==4.2.0; extra == "dev"
Requires-Dist: aio-pika==9.3.0; extra == "dev"
Requires-Dist: aiokafka==0.10.0; extra == "dev"
Requires-Dist: requests==2.*; extra == "dev"
Requires-Dist: pytest~=7.4.2; extra == "dev"
Requires-Dist: pytest-asyncio~=0.21.1; extra == "dev"
Requires-Dist: pytest-env==0.6.2; extra == "dev"
Requires-Dist: cryptography==42.0.2; extra == "dev"
Requires-Dist: asyncmy==0.2.9; extra == "dev"
Requires-Dist: redis>=5.0.0; extra == "dev"
Requires-Dist: aiobreaker>=0.3.0; extra == "dev"
Provides-Extra: examples
Requires-Dist: fastapi==0.109.*; extra == "examples"
Requires-Dist: faststream[kafka]==0.5.28; extra == "examples"
Requires-Dist: faker>=37.12.0; extra == "examples"
Requires-Dist: uvicorn==0.32.0; extra == "examples"
Requires-Dist: aiohttp==3.13.2; extra == "examples"
Provides-Extra: kafka
Requires-Dist: aiokafka==0.10.0; extra == "kafka"
Provides-Extra: protobuf
Requires-Dist: protobuf==4.25.5; extra == "protobuf"
Provides-Extra: rabbit
Requires-Dist: aio-pika==9.3.0; extra == "rabbit"
Dynamic: license-file
